genitosdk/__init__.py
genitosdk/film_client.py
genitosdk/film_config.py
genitosdk/schemas/__init__.py
genitosdk/schemas/schemas.py
genitosdk-0.0.4.dist-info/METADATA
genitosdk-0.0.4.dist-info/WHEEL
genitosdk-0.0.4.dist-info/top_level.txt
genitosdk-0.0.4.dist-info/RECORD
